{
  "TV_Data": {
    "Admob_Settings": {
      "ads_Delay": 0,
      "ads_On_Cancel_Delay": 0,
      "applovin_ads": {
        "ads_app_id": "WELTwtWXafsts82Q1HIQ2v7OeEHUtGHOUcsPTMx21owuxzIzEbNGUVf8kycbCu-hVr5zB10Dpx5luOh7-4NSZ2",
        "is_Ads": true,
        "is_Banner_Ads": true,
        "is_Interstitial_Ads": true,
        "visibility_Percentage": 0
      },
      "appnext_ads": {
        "banner_ad_unit_id": "957c9114-4c95-4259-bfdd-0ac4a6d8f4e1",
        "interstitial_ad_unit_id": "2aa93ef9-381a-4b15-945a-86d4eba9ff0c",
        "is_Ads": true,
        "is_Banner_Ads": true,
        "is_Interstitial_Ads": true,
        "rewarded_video_ad_unit_id": "8c9e6a25-14b7-4184-89a5-f1e14be59b1b",
        "visibility_Percentage": 0
      },
      "default_Ads": "facebook_ads",
      "facebook_ads": {
        "ads_app_id": "417762135358078",
        "banner_ad_unit_id": "417762135358078_417762335358058",
        "interstitial_ad_unit_id": "417762135358078_417762628691362",
        "is_Ads": true,
        "is_Banner_Ads": true,
        "is_Interstitial_Ads": true,
        "visibility_Percentage": 1
      },
      "google_ads": {
        "ads_app_id": "ca-app-pub-9435847929752889~3251315030",
        "banner_ad_unit_id": "ca-app-pub-9435847929752889/9805115099",
        "interstitial_ad_unit_id": "ca-app-pub-9435847929752889/9122588812",
        "is_Ads": true,
        "is_Banner_Ads": true,
        "is_Interstitial_Ads": true,
        "native_ad_unit_id": "ca-app-pub-9435847929752889/3622441001",
        "rewarded_video_ad_unit_id": "ca-app-pub-9435847929752889/3622441001",
        "visibility_Percentage": 100
      },
      "is_Banner_Ads": true,
      "is_Interstitial_Ads": true,
      "is_StreamPlayer_Banner_Ads": true,
      "startapp_ads": {
        "ads_app_id": "201571398",
        "is_Ads": true,
        "is_Banner_Ads": true,
        "is_Interstitial_Ads": true,
        "visibility_Percentage": 0
      }
    },
    "Ads_Popup": {
      "ads_app_package_id": "com.instantbits.cast.webvideo",
      "ads_description": "Take your Spectrum TV experience with you! With the Spectrum TV App, you can enjoy up to 250 live TV channels and up to 30,000 On Demand TV shows and movies when you're connected to your Spectrum Internet WiFi network at home. Plus, when you're on the go, enjoy up to 150 live channels and up to 20,000 On Demand titles anywhere you have an internet connection. (See note on availability below.)",
      "ads_download_popup_description": "To Install this app you need to follow below steps. :\n\n(1). Press \"START\" button.\n(2). If It will ask for permission please allow.\n(3). It will open download dialog and please wait till download completion.\n(4). After you can see \"INSTALL\" button, press \"INSTALL\" button.\n(5). After It will popup for installation screen and then \"INSTALL\" it.\n(6). After installation complete press \"OPEN\" button and enjoy app.",
      "ads_download_popup_title": "App Installation",
      "ads_remind_id": "",
      "ads_thumbnail_url": "https://www.apkmirror.com/wp-content/themes/APKMirror/ap_resize/ap_resize.php?src=https%3A%2F%2Fwww.apkmirror.com%2Fwp-content%2Fuploads%2F2018%2F02%2F5a8e13c776935.png&w=96&h=96&q=100",
      "ads_title": "Spectrum TV",
      "ads_website_url": "https://www.youtube.com/watch?v=KJJRLQdFz9w&t=447s",
      "download_url": "https://www.apkmirror.com/wp-content/themes/APKMirror/download.php?id=235411",
      "filename": "RUTU_ADS.apk",
      "is_system_browser": true,
      "progress_download_message": "App Downloading...",
      "progress_install_message": "Install Now"
    },
    "Affiliate_Popup": {
      "affiliate_btn_name": "Best OFFER",
      "affiliate_dialog_title": "Buy Now",
      "affiliate_product_image_url": "http://www.directd.com.my/content/images/thumbs/0020704_xiaomi-redmi-5-plus-3gb-ram-32gb-rom-4gb-ram-64gb-rom.png",
      "affiliate_product_title": "Redmi 5A (Rose Gold, 32 GB)  (3 GB RAM)",
      "affiliate_product_url": "https://www.flipkart.com/redmi-5a-rose-gold-32-gb/p/itmf2fwcumw7ghwy?pid=MOBEZWXE8NSAZ73T&srno=s_1_1&otracker=search&lid=LSTMOBEZWXE8NSAZ73TZT8DKM&fm=SEARCH&iid=3b2f12e6-64f5-4e2b-a76a-bb168cfe30ea.MOBEZWXE8NSAZ73T.SEARCH&ppt=Store%20Browse&ppn=Search%20Page&ssid=4fz5otakk00000001522215027694&qH=f8a10d5a7adb2998",
      "affiliate_remind_id": "",
      "is_system_browser": true
    },
    "App_Download_Setting": {
      "filename": "RUTU_APP.apk",
      "popup_description": "To Activate Plugin you need to follow below steps. :\n\n(1). Press \"SETUP\" button.\n(2). If It will ask for permission please allow.\n(3). It will open download dialog and please wait till download completion.\n(4). After you can see \"INSTALL\" button, press \"INSTALL\" button.\n(5). After It will popup for installation screen and then \"INSTALL\" it.\n(6). After installation complete press \"DONE\" button.\n(7). Come back to Pocket TV and you will see your plugin activated.",
      "popup_title": "Plugin Installation",
      "progress_download_message": "Downloading...",
      "progress_install_message": "Install Now"
    },
    "App_Information_Popup": {
      "info_guide_image_url": "https://raw.githubusercontent.com/rutumaster/Pocket-TV/Final-Apps/COMMON/Images-PocketTV/Other/Remove-Ads.jpg?alt=media&token=a583a7b4-94ed-4cb4-ae6f-41db53378f5b",
      "info_initial_description": "Are you tired for lots of Ads?\nwe provide support of \"Remove Ads\".\nHere you can remove ads permanently from app.\nFor that you have to follow two simple steps :\n\n(1). Open menu and select \"Remove Ads\" option.\n(2). Select first button shown in above image and do payment.",
      "info_remind_id": "1",
      "info_title": "Remove Ads Guidance"
    },
    "Channel_List": {
      "main_1": {
        "id" : 1,
        "auto_banner" : false,
        "auto_thumbnail" : false,
        "name" : "Russia",
        "sub_name" : "Channels",
        "thumbnail_url" : "=============",
        "banner_url" : "=============",
        "sub": {
          "sub_1": {
            "id" : 1,
            "name" : "Telekanal Doktor",
            "sub_name" : "",
            "banner_url" : "https://www.lyngsat-logo.com/logo/tv/tt/telekanal_doktor_ru.png",
            "thumbnail_url" : "https://www.lyngsat-logo.com/logo/tv/tt/telekanal_doktor_ru.png",
            "satellite_data_url" : "https://astra.ses/channels/telekanal-doktor"
          }
        }
      },
      "main_2": {
        "id" : 2,
        "auto_banner" : false,
        "auto_thumbnail" : false,
        "name" : "Turkey",
        "sub_name" : "Channels",
        "thumbnail_url" : "=============",
        "banner_url" : "=============",
        "sub": {
          "sub_1": {
            "id" : 1,
            "name" : "V!va",
            "sub_name" : "",
            "banner_url" : "https://www.lyngsat-logo.com/logo/tv/vv/viva_tr.png",
            "thumbnail_url" : "https://www.lyngsat-logo.com/logo/tv/vv/viva_tr.png",
            "satellite_data_url" : "https://astra.ses/channels/telekanal-doktor"
          },
          "sub_2": {
            "id" : 2,
            "name" : "Sony Channel Türkiye",
            "sub_name" : "",
            "banner_url" : "https://www.lyngsat-logo.com/logo/tv/ss/sony_channel_in.png",
            "thumbnail_url" : "https://www.lyngsat-logo.com/logo/tv/ss/sony_channel_in.png",
            "satellite_data_url" : "https://astra.ses/channels/telekanal-doktor"
          },
          "sub_3": {
            "id" : 3,
            "name" : "Planet Türk",
            "sub_name" : "",
            "banner_url" : "https://www.lyngsat-logo.com/logo/tv/pp/planet_turk.png",
            "thumbnail_url" : "https://www.lyngsat-logo.com/logo/tv/pp/planet_turk.png",
            "satellite_data_url" : "https://astra.ses/channels/telekanal-doktor"
          },
          "sub_4": {
            "id" : 4,
            "name" : "Sony Mutfak",
            "sub_name" : "",
            "banner_url" : "https://www.lyngsat-logo.com/logo/tv/ss/sony-mutfak-in-tr.png",
            "thumbnail_url" : "https://www.lyngsat-logo.com/logo/tv/ss/sony-mutfak-in-tr.png",
            "satellite_data_url" : "https://astra.ses/channels/telekanal-doktor"
          },
          "sub_5": {
            "id" : 5,
            "name" : "Planet Çocuk",
            "sub_name" : "",
            "banner_url" : "https://www.lyngsat-logo.com/logo/tv/pp/planet-cocuk-tr.png",
            "thumbnail_url" : "https://www.lyngsat-logo.com/logo/tv/pp/planet-cocuk-tr.png",
            "satellite_data_url" : "https://astra.ses/channels/telekanal-doktor"
          },
          "sub_6": {
            "id" : 6,
            "name" : "Radyo Viva",
            "sub_name" : "",
            "banner_url" : "https://www.lyngsat-logo.com/logo/radio/rr/radyo_viva.png",
            "thumbnail_url" : "https://www.lyngsat-logo.com/logo/radio/rr/radyo_viva.png",
            "satellite_data_url" : "https://astra.ses/channels/telekanal-doktor"
          },
          "sub_7": {
            "id" : 7,
            "name" : "Show Radyo",
            "sub_name" : "",
            "banner_url" : "https://www.lyngsat-logo.com/logo/radio/ss/show_radyo_tr.png",
            "thumbnail_url" : "https://www.lyngsat-logo.com/logo/radio/ss/show_radyo_tr.png",
            "satellite_data_url" : "https://astra.ses/channels/telekanal-doktor"
          }
        }
      },
      "main_3": {
        "id" : 3,
        "auto_banner" : false,
        "auto_thumbnail" : false,
        "name" : "Other Country",
        "sub_name" : "Channels",
        "thumbnail_url" : "=============",
        "banner_url" : "=============",
        "sub": {
          "sub_1": {
            "id" : 1,
            "name" : "TrFilm TV",
            "sub_name" : "",
            "banner_url" : "/themes/custom/astra/assets/images/channels-default.svg",
            "thumbnail_url" : "/themes/custom/astra/assets/images/channels-default.svg",
            "satellite_data_url" : "https://astra.ses/channels/telekanal-doktor"
          }
        }
      },
      "main_4": {
        "id" : 4,
        "auto_banner" : false,
        "auto_thumbnail" : false,
        "name" : "India",
        "sub_name" : "Channels",
        "thumbnail_url" : "=============",
        "banner_url" : "=============",
        "sub": {
          "sub_1": {
            "id" : 1,
            "name" : "Sony Channel Türkiye",
            "sub_name" : "",
            "banner_url" : "https://www.lyngsat-logo.com/logo/tv/ss/sony_channel_in.png",
            "thumbnail_url" : "https://www.lyngsat-logo.com/logo/tv/ss/sony_channel_in.png",
            "satellite_data_url" : "https://astra.ses/channels/telekanal-doktor"
          },
          "sub_2": {
            "id" : 2,
            "name" : "Sony Mutfak",
            "sub_name" : "",
            "banner_url" : "https://www.lyngsat-logo.com/logo/tv/ss/sony-mutfak-in-tr.png",
            "thumbnail_url" : "https://www.lyngsat-logo.com/logo/tv/ss/sony-mutfak-in-tr.png",
            "satellite_data_url" : "https://astra.ses/channels/telekanal-doktor"
          },
          "sub_3": {
            "id" : 3,
            "name" : "Zee TV UK",
            "sub_name" : "",
            "banner_url" : "https://www.lyngsat-logo.com/logo/tv/zz/zee-tv-in.png",
            "thumbnail_url" : "https://www.lyngsat-logo.com/logo/tv/zz/zee-tv-in.png",
            "satellite_data_url" : "https://astra.ses/channels/telekanal-doktor"
          }
        }
      },
      "main_5": {
        "id" : 5,
        "auto_banner" : false,
        "auto_thumbnail" : false,
        "name" : "United Kingdom",
        "sub_name" : "Channels",
        "thumbnail_url" : "=============",
        "banner_url" : "=============",
        "sub": {
          "sub_1": {
            "id" : 1,
            "name" : "Climax",
            "sub_name" : "",
            "banner_url" : "https://www.lyngsat-logo.com/logo/tv/cc/climax_uk.png",
            "thumbnail_url" : "https://www.lyngsat-logo.com/logo/tv/cc/climax_uk.png",
            "satellite_data_url" : "https://astra.ses/channels/telekanal-doktor"
          },
          "sub_2": {
            "id" : 2,
            "name" : "FreeSports",
            "sub_name" : "",
            "banner_url" : "https://www.lyngsat-logo.com/logo/tv/ff/freesports-uk.png",
            "thumbnail_url" : "https://www.lyngsat-logo.com/logo/tv/ff/freesports-uk.png",
            "satellite_data_url" : "https://astra.ses/channels/telekanal-doktor"
          },
          "sub_3": {
            "id" : 3,
            "name" : "Zee TV UK",
            "sub_name" : "",
            "banner_url" : "https://www.lyngsat-logo.com/logo/tv/zz/zee-tv-in.png",
            "thumbnail_url" : "https://www.lyngsat-logo.com/logo/tv/zz/zee-tv-in.png",
            "satellite_data_url" : "https://astra.ses/channels/telekanal-doktor"
          },
          "sub_4": {
            "id" : 4,
            "name" : "LFC TV",
            "sub_name" : "",
            "banner_url" : "https://www.lyngsat-logo.com/logo/tv/ll/liverpool_football_club.png",
            "thumbnail_url" : "https://www.lyngsat-logo.com/logo/tv/ll/liverpool_football_club.png",
            "satellite_data_url" : "https://astra.ses/channels/telekanal-doktor"
          },
          "sub_5": {
            "id" : 5,
            "name" : "Sky On Demand B",
            "sub_name" : "",
            "banner_url" : "https://www.lyngsat-logo.com/logo/tv/ss/sky_uk_anytime_b.png",
            "thumbnail_url" : "https://www.lyngsat-logo.com/logo/tv/ss/sky_uk_anytime_b.png",
            "satellite_data_url" : "https://astra.ses/channels/telekanal-doktor"
          },
          "sub_6": {
            "id" : 6,
            "name" : "Real Lives",
            "sub_name" : "",
            "banner_url" : "https://www.lyngsat-logo.com/logo/tv/rr/real_lives_uk.png",
            "thumbnail_url" : "https://www.lyngsat-logo.com/logo/tv/rr/real_lives_uk.png",
            "satellite_data_url" : "https://astra.ses/channels/telekanal-doktor"
          },
          "sub_7": {
            "id" : 7,
            "name" : "More 4 Ireland",
            "sub_name" : "",
            "banner_url" : "https://www.lyngsat-logo.com/logo/tv/cc/channel_4_more4_ie.png",
            "thumbnail_url" : "https://www.lyngsat-logo.com/logo/tv/cc/channel_4_more4_ie.png",
            "satellite_data_url" : "https://astra.ses/channels/telekanal-doktor"
          },
          "sub_8": {
            "id" : 8,
            "name" : "TJC",
            "sub_name" : "",
            "banner_url" : "https://www.lyngsat-logo.com/logo/tv/tt/the_jewellery_channel_uk.png",
            "thumbnail_url" : "https://www.lyngsat-logo.com/logo/tv/tt/the_jewellery_channel_uk.png",
            "satellite_data_url" : "https://astra.ses/channels/telekanal-doktor"
          }
        }
      },
      "main_6": {
        "id" : 6,
        "auto_banner" : false,
        "auto_thumbnail" : false,
        "name" : "Ireland",
        "sub_name" : "Channels",
        "thumbnail_url" : "=============",
        "banner_url" : "=============",
        "sub": {
          "sub_1": {
            "id" : 1,
            "name" : "RTÉ Jr",
            "sub_name" : "",
            "banner_url" : "https://www.lyngsat-logo.com/logo/tv/rr/rte_jr_tv.png",
            "thumbnail_url" : "https://www.lyngsat-logo.com/logo/tv/rr/rte_jr_tv.png",
            "satellite_data_url" : "https://astra.ses/channels/telekanal-doktor"
          },
          "sub_2": {
            "id" : 2,
            "name" : "Oireachtas TV",
            "sub_name" : "",
            "banner_url" : "https://www.lyngsat-logo.com/logo/tv/oo/oireachtas_tv_ie.png",
            "thumbnail_url" : "https://www.lyngsat-logo.com/logo/tv/oo/oireachtas_tv_ie.png",
            "satellite_data_url" : "https://astra.ses/channels/telekanal-doktor"
          },
          "sub_3": {
            "id" : 3,
            "name" : "RTÉ One +1",
            "sub_name" : "",
            "banner_url" : "https://www.lyngsat-logo.com/logo/tv/rr/rte_one_plus1.png",
            "thumbnail_url" : "https://www.lyngsat-logo.com/logo/tv/rr/rte_one_plus1.png",
            "satellite_data_url" : "https://astra.ses/channels/telekanal-doktor"
          },
          "sub_4": {
            "id" : 4,
            "name" : "RTÉ News Now",
            "sub_name" : "",
            "banner_url" : "https://www.lyngsat-logo.com/logo/tv/rr/rte_news_now.png",
            "thumbnail_url" : "https://www.lyngsat-logo.com/logo/tv/rr/rte_news_now.png",
            "satellite_data_url" : "https://astra.ses/channels/telekanal-doktor"
          },
          "sub_5": {
            "id" : 5,
            "name" : "More 4 Ireland",
            "sub_name" : "",
            "banner_url" : "https://www.lyngsat-logo.com/logo/tv/cc/channel_4_more4_ie.png",
            "thumbnail_url" : "https://www.lyngsat-logo.com/logo/tv/cc/channel_4_more4_ie.png",
            "satellite_data_url" : "https://astra.ses/channels/telekanal-doktor"
          }
        }
      },
      "main_7": {
        "id" : 7,
        "auto_banner" : false,
        "auto_thumbnail" : false,
        "name" : "United States",
        "sub_name" : "Channels",
        "thumbnail_url" : "=============",
        "banner_url" : "=============",
        "sub": {
          "sub_1": {
            "id" : 1,
            "name" : "Hope Radio",
            "sub_name" : "",
            "banner_url" : "https://www.lyngsat-logo.com/logo/radio/hh/hope_channel_radio_de.png",
            "thumbnail_url" : "https://www.lyngsat-logo.com/logo/radio/hh/hope_channel_radio_de.png",
            "satellite_data_url" : "https://astra.ses/channels/telekanal-doktor"
          }
        }
      },
      "main_8": {
        "id" : 8,
        "auto_banner" : false,
        "auto_thumbnail" : false,
        "name" : "Germany",
        "sub_name" : "Channels",
        "thumbnail_url" : "=============",
        "banner_url" : "=============",
        "sub": {
          "sub_1": {
            "id" : 1,
            "name" : "Hope Radio",
            "sub_name" : "",
            "banner_url" : "https://www.lyngsat-logo.com/logo/radio/hh/hope_channel_radio_de.png",
            "thumbnail_url" : "https://www.lyngsat-logo.com/logo/radio/hh/hope_channel_radio_de.png",
            "satellite_data_url" : "https://astra.ses/channels/telekanal-doktor"
          },
          "sub_2": {
            "id" : 2,
            "name" : "Lokal TV Portal",
            "sub_name" : "",
            "banner_url" : "http://www.lyngsat-logo.com/logo/tv/ll/lokal_tv_de.png",
            "thumbnail_url" : "http://www.lyngsat-logo.com/logo/tv/ll/lokal_tv_de.png",
            "satellite_data_url" : "https://astra.ses/channels/telekanal-doktor"
          },
          "sub_3": {
            "id" : 3,
            "name" : "Lokal TV Portal",
            "sub_name" : "",
            "banner_url" : "http://www.lyngsat-logo.com/logo/tv/ll/lokal_tv_de.png",
            "thumbnail_url" : "http://www.lyngsat-logo.com/logo/tv/ll/lokal_tv_de.png",
            "satellite_data_url" : "https://astra.ses/channels/telekanal-doktor"
          },
          "sub_4": {
            "id" : 4,
            "name" : "Lokal TV Portal",
            "sub_name" : "",
            "banner_url" : "http://www.lyngsat-logo.com/logo/tv/ll/lokal_tv_de.png",
            "thumbnail_url" : "http://www.lyngsat-logo.com/logo/tv/ll/lokal_tv_de.png",
            "satellite_data_url" : "https://astra.ses/channels/telekanal-doktor"
          },
          "sub_5": {
            "id" : 5,
            "name" : "Lokal TV Portal",
            "sub_name" : "",
            "banner_url" : "http://www.lyngsat-logo.com/logo/tv/ll/lokal_tv_de.png",
            "thumbnail_url" : "http://www.lyngsat-logo.com/logo/tv/ll/lokal_tv_de.png",
            "satellite_data_url" : "https://astra.ses/channels/telekanal-doktor"
          },
          "sub_6": {
            "id" : 6,
            "name" : "Lokal TV Portal",
            "sub_name" : "",
            "banner_url" : "http://www.lyngsat-logo.com/logo/tv/ll/lokal_tv_de.png",
            "thumbnail_url" : "http://www.lyngsat-logo.com/logo/tv/ll/lokal_tv_de.png",
            "satellite_data_url" : "https://astra.ses/channels/telekanal-doktor"
          },
          "sub_7": {
            "id" : 7,
            "name" : "Lokal TV Portal",
            "sub_name" : "",
            "banner_url" : "http://www.lyngsat-logo.com/logo/tv/ll/lokal_tv_de.png",
            "thumbnail_url" : "http://www.lyngsat-logo.com/logo/tv/ll/lokal_tv_de.png",
            "satellite_data_url" : "https://astra.ses/channels/telekanal-doktor"
          },
          "sub_8": {
            "id" : 8,
            "name" : "Lokal TV Portal",
            "sub_name" : "",
            "banner_url" : "http://www.lyngsat-logo.com/logo/tv/ll/lokal_tv_de.png",
            "thumbnail_url" : "http://www.lyngsat-logo.com/logo/tv/ll/lokal_tv_de.png",
            "satellite_data_url" : "https://astra.ses/channels/telekanal-doktor"
          },
          "sub_9": {
            "id" : 9,
            "name" : "Lokal TV Portal",
            "sub_name" : "",
            "banner_url" : "https://www.lyngsat-logo.com/logo/tv/ll/lokal_tv_de.png",
            "thumbnail_url" : "https://www.lyngsat-logo.com/logo/tv/ll/lokal_tv_de.png",
            "satellite_data_url" : "https://astra.ses/channels/telekanal-doktor"
          }
        }
      }
    },
    "Chromecast_Setting": {
      "cast_agent": "09",
      "cast_guide_image_url": "https://raw.githubusercontent.com/rutumaster/Pocket-TV/Final-Apps/COMMON/Images-PocketTV/Other/Chromecast_Notification.jpg?alt=media&token=3a2c14f2-20d2-4dfe-9eed-336544df9e09",
      "cast_package_name": "com.instantbits.cast.webvideo",
      "inapp_chromecast_message": "If you want to play video on you TV.<br><br>Then you should purchase this service.<br><br>You will get chromecast support from Pocket TV.",
      "is_inapp_chromecast" : "true",
      "inapp_chromecast_sku" : "com.pockettv.chromecast",
      "cast_referer": "https://www.metube.id",
      "download_url": "https://github.com/rutumaster/Pocket-TV/raw/Final-Apps/COMMON/APKS/ChromeCast.apk",
      "filename": "RUTU_CHROMECAST.apk",
      "initial_cast_message": "Do you need Chromecast support then follow below steps :<br><br>(1). Press \"SETUP\" button.<br>(2). If It will ask for permission please allow.<br>(3). It will open download dialog and please wait till download completion.<br>(4). After you can see \"INSTALL\" button, press \"INSTALL\" button.<br>(5). After It will popup for installation screen and then \"INSTALL\" it.<br>(6). After installation complete press \"DONE\" button.<br>(7). Come back to Pocket TV and you will see your plugin activated.<br>(9). If you can't setup then : <a href='https://github.com/rutumaster/Pocket-TV/raw/Final-Apps/COMMON/APKS/ChromeCast.apk'>DOWNLOAD HERE</a><br><br>",
      "progress_download_message": "Downloading...",
      "progress_install_message": "Install Now",
      "success_cast_message": "Now You can Chromecast Your Video From Player."
    },
    "Purchase_Restore":
    {
      "is_Purchase_Restore" : false,
      "title" : "Restore App",
      "guide_image_url" : "",
      "description" : "If you purchased Previously?\n\nThen you have to press \"Restore\" Button to restore all purchase."
    },
    "Inapp_Purchase_Settings" :
    {
      "purcahse_package_id" : "com.allinone.purchase",
      "download_url" : "https://raw.githubusercontent.com/rutumaster/Pocket-TV/Final-Apps/All-In-One_Purcahse/APK/All%20In%20One%20Purchase.apk",
      "filename" : "PURCHASE.apk",
      "purcahse_title": "Purchase App",
      "purcahse_message": "If you want to Purcahse then you have to install Purchase App.\nand then try again to purchase from here once again.",
      "progress_download_message" : "Downloading...",
      "progress_install_message" : "Install Now",
      "inapp_base64EncodedPublicKey" : "MIIBIjANBgkqhkiG9w0BAQEFAAOCAQ8AMIIBCgKCAQEApLE+5061d1CMY+2i9gmWOfp/2frJ8am0gZcck7l7VxwUKLsHmWfapCKj2hKxJWb2SS9O9WAAKLLav/xqCz3KjaHpPT/h1aMiBV7UbhiXU0upDxndPjRWqIn2gsAkxiRoOcAxh0d365YL5qatzGqBOWw2tGwnEc5f1bgmZuCs+wgXXwjiEUY1eHLwjc0wsLT/8H9zpARUhsTh3eefHDesg6Yakfi9F+l8B/Y6tuWheWdB1WFwrDFJuiXv2Kq6Dcb80MiPPNIhO2wIf+1CsVDvgsRQGBDKJFPBpKznNdibDiYL0qS7R1Xu3Bh63Mvt9ns3yKQTR0yQ4x9xRvpRIk7o+QIDAQAB"
    },
    "Clone_URL_Updater": {
      "azhar_URL": "https://www.kikflix.com/livetv_app/static_contents/api.php?latest",
      "diltv_URL": "https://www.diltv.org/apps/output.php/playlist?type=xml&deviceSn=pakentnews&token=",
      "diltvdhamaka_URL": "https://www.diltv.org/apps/output.php/playlist?type=xml&deviceSn=dhamkatv1&token=",
      "swift_URL": "http://swiftstreamz.com/SwiftLive/api.php?latest=5000"
    },
    "Disclaimer_Setting": {
      "initial_disclaimer_message": "Pocket TV does not warrant the completeness, timeliness or accuracy of any of the data contained in this app and may make changes thereto at any time in its sole discretion without notice. Further, all information conveyed hereby is provided to users “AS IS”. In no event shall Pocket TV be liable for any damages of any kind related to the use or misuse of Information provided hereby.\nWe do not host any link or streams. If you found any copyrighted channel, please write us in feedback with appropriate link host for its removal."
    },
    "Display_Settings": {
      "default_Banner_Url": "https://www.efalia.com/wp-content/uploads/2015/01/fotolia_84282280-maquette-maintenance-2.jpg",
      "default_Thumbnail_Url": "https://www.efalia.com/wp-content/uploads/2015/01/fotolia_84282280-maquette-maintenance-2.jpg",
      "is_Hd_Banner": true,
      "is_Hd_Thumbnail": false,
      "is_Main_Banner": false,
      "is_Main_Banner_Text": true,
      "is_Sub_Banner": false,
      "is_Sub_Banner_Text": true,
      "main_Banner_Duration": 5000,
      "main_Banner_Height": 200,
      "main_Grid_Margin": 7,
      "main_L_Mob": 3,
      "main_L_Tab": 4,
      "main_P_Mob": 2,
      "main_P_Tab": 3,
      "sub_Banner_Duration": 5000,
      "sub_Banner_Height": 200,
      "sub_Grid_Margin": 7,
      "sub_L_Mob": 4,
      "sub_L_Tab": 5,
      "sub_P_Mob": 3,
      "sub_P_Tab": 4,
      "is_custom_Thumb": true,
      "custom_Thumb_BG_Color": "#fcf9f4",
      "custom_Thumb_Txt_Color": "#ed5a64"
    },
    "Donation_Settings": {
      "donation_image_url": "https://alsride.org.au/wp-content/uploads/2017/03/donation.png",
      "donation_title": "Donate Us",
      "donation_url": "https://www.paypal.me/PocketTV",
      "initial_donation_message": "If you are Satisfied with Pocket TV, Donate Us and Help to Improve.\nDonation is the key to keep our app running and active. Please click on the \"DONATE\" button.\nEvery single bit of donations is very important to us and give your hands to us. \n\nThank you\nPocket TV Developer",
      "isDonation": false,
      "is_system_browser": true
    },
    "Feedback_Setting": {
      "feedback_CC_Email": "rutu.news@gmail.com",
      "feedback_Email": "rutu.inc@gmail.com",
      "feedback_Message": "Hi,\n\n\nYour Feedback Pocket TV Rocks! I would like to give you some feedback: ",
      "feedback_Subject": "Feedback on Pocket TV",
      "feedback_Title": "Send Feedback",
      "initial_Feedback_Text": "If you have any kind of query, Then mail us.\nWe will resolve it."
    },
    "Intro_Slider": {
      "slider_0": {
        "dot_Active_Color": "#C8FFFFFF",
        "dot_InActive_Color": "#4B000000",
        "id": 0,
        "img_Url": "https://raw.githubusercontent.com/rutumaster/Pocket-TV/Final-Apps/COMMON/Images-PocketTV/Intro%20Slider/World.png?alt=media&token=92a62012-f679-4bdc-87a9-5ec8e30fa74e",
        "initial_desc": "20+ Country and Regional Channels",
        "page_Color": "#586162",
        "title": "Worldwide"
      },
      "slider_1": {
        "dot_Active_Color": "#C8FFFFFF",
        "dot_InActive_Color": "#4B000000",
        "id": 1,
        "img_Url": "https://raw.githubusercontent.com/rutumaster/Pocket-TV/Final-Apps/COMMON/Images-PocketTV/Intro%20Slider/Sports-3.png?alt=media&token=197a585d-9e64-4395-af42-5c2fe568c57b",
        "initial_desc": "All Sports Live Channels",
        "page_Color": "#2977b9",
        "title": "Sports"
      },
      "slider_2": {
        "dot_Active_Color": "#C8FFFFFF",
        "dot_InActive_Color": "#4B000000",
        "id": 2,
        "img_Url": "https://raw.githubusercontent.com/rutumaster/Pocket-TV/Final-Apps/COMMON/Images-PocketTV/Intro%20Slider/news-2.png?alt=media&token=b5f5910b-18c0-4a17-a066-7803edcec6e4",
        "initial_desc": "All News Live Channels",
        "page_Color": "#a90000",
        "title": "News"
      },
      "slider_3": {
        "dot_Active_Color": "#C8FFFFFF",
        "dot_InActive_Color": "#4B000000",
        "id": 3,
        "img_Url": "https://raw.githubusercontent.com/rutumaster/Pocket-TV/Final-Apps/COMMON/Images-PocketTV/Intro%20Slider/entertainment-2.png?alt=media&token=a15ca4c0-19ee-4509-b279-17214f718a6f",
        "initial_desc": "All Entertainment Live Channels",
        "page_Color": "#2da1be",
        "title": "Entertainment"
      },
      "slider_4": {
        "dot_Active_Color": "#C8FFFFFF",
        "dot_InActive_Color": "#4B000000",
        "id": 4,
        "img_Url": "https://raw.githubusercontent.com/rutumaster/Pocket-TV/Final-Apps/COMMON/Images-PocketTV/Intro%20Slider/wild-life--2.png?alt=media&token=82e30eb3-3838-4692-bdf4-04f511fd414e",
        "initial_desc": "All Wild Life / Science Live Channels",
        "page_Color": "#8eb021",
        "title": "Wild Life / Science"
      },
      "slider_5": {
        "dot_Active_Color": "#C8FFFFFF",
        "dot_InActive_Color": "#4B000000",
        "id": 5,
        "img_Url": "https://raw.githubusercontent.com/rutumaster/Pocket-TV/Final-Apps/COMMON/Images-PocketTV/Intro%20Slider/Religious.png?alt=media&token=42aa5228-c306-4e4f-bd81-a5ae351956bb",
        "initial_desc": "All Relegious Live Channels",
        "page_Color": "#ffa800",
        "title": "Relegious"
      },
      "slider_6": {
        "dot_Active_Color": "#C8FFFFFF",
        "dot_InActive_Color": "#4B000000",
        "id": 6,
        "img_Url": "https://raw.githubusercontent.com/rutumaster/Pocket-TV/Final-Apps/COMMON/Images-PocketTV/Intro%20Slider/Movie-2.png?alt=media&token=b86c3a10-d37b-4ce2-ab8e-469260bdee0a",
        "initial_desc": "All Movies Free",
        "page_Color": "#5b48a2",
        "title": "Movies"
      },
      "slider_7": {
        "dot_Active_Color": "#C8FFFFFF",
        "dot_InActive_Color": "#4B000000",
        "id": 7,
        "img_Url": "https://raw.githubusercontent.com/rutumaster/Pocket-TV/Final-Apps/COMMON/Images-PocketTV/Intro%20Slider/songs-2.png?alt=media&token=16d5ad1b-9a8f-4c17-8fd7-780022bcd0d2",
        "initial_desc": "All Songs Free",
        "page_Color": "#79302a",
        "title": "Songs"
      },
      "slider_8": {
        "dot_Active_Color": "#C8FFFFFF",
        "dot_InActive_Color": "#4B000000",
        "id": 8,
        "img_Url": "https://raw.githubusercontent.com/rutumaster/Pocket-TV/Final-Apps/COMMON/Images-PocketTV/Intro%20Slider/kidz-2.png?alt=media&token=8cb93373-53a2-4f83-9124-32823407b16d",
        "initial_desc": "All Kids Live Channels",
        "page_Color": "#b7a271",
        "title": "Kids Zone"
      }
    },
    "Live_Streams_Setting": {
      "HelloLogin": "http://swiftstreamz.com/token624.php",
      "HelloUrl": "http://185.21.217.31:7071/",
      "HelloUrl1": "http://185.21.216.192:7071/",
      "LiveTvLogin": "http://swiftstreamz.com/token622.php",
      "LiveTvUrl": "http://78.129.252.222:8081/",
      "Password": "@Swift11#:@Swift11#",
      "PasswordHello": "@Swift14#:@Swift14#",
      "PasswordLiveTv": "@Swift12#:@Swift12#",
      "PasswordNew": "@Swift13#:@Swift13#",
      "channel_not_play_error_message": "Channel not play because server is down.\nTry After Some Time",
      "dhamaka_encode_password": "bagi:bagi",
      "dhamaka_encode_url": "https://aps.dynns.com/keys/android_encodes.php",
      "dhamaka_main_password": "AltafhussainMQM:Pakistanzindabad",
      "dhamaka_main_url": "https://www.boxtvhd.com/androidapsbackup/dhamkatv.php",
      "dhamakatvUrl": {
        "sub1": {
          "url": "http://185.59.221.171:8081/"
        },
        "sub2": {
          "url": "http://185.59.221.176:8081/"
        },
        "sub3": {
          "url": "http://130.185.144.110:8081/"
        },
        "sub4": {
          "url": "http://live-pull-02-hls-1369.5centscdn.com/"
        },
        "sub5": {
          "url": "http://185.59.221.72:8081/"
        },
        "sub6": {
          "url": "http://movfr.ddns.net:8081/"
        },
        "sub7": {
          "url": "http://50.7.198.18:8081/"
        },
        "sub8": {
          "url": "http://198.16.104.2:8081/"
        }
      },
      "eboundUrl": "http://cdn.ebound.tv",
      "isAutoTokenUrlFromMainUrl": true,
      "loginUrl": "http://swiftstreamz.com/token621.php",
      "loginUrlNew": "http://swiftstreamz.com/token623.php",
      "mainPass": "SwiftStreamz:@SwiftStreamz@",
      "mainUrl": "http://swiftstreamz.com/SwiftLive/swiftlive.php",
      "nexgtvPass": "@Swift15#:@Swift15#",
      "nexgtvToken": "http://swiftstreamz.com/token626.php",
      "nexgtvUrl": "http://93.174.93.84:8081/"
    },
    "Other_Player_Unlock": {
      "inapp_other_player_sku" : "com.pockettv.otherplayeroption",
      "initial_other_player_message": "If you want to play video on you favorite video player.\n\nThen you should purchase this service.\n\nYou will get player chooser while you try to play any video or channel from Pocket TV.",
      "isAppPlayer": true,
      "isWebviewPlayer": false,
      "isOtherPlayerOption": false,
      "is_Inapp_Purchase": false,
      "other_player_image_url": "https://raw.githubusercontent.com/rutumaster/Pocket-TV/Final-Apps/COMMON/Images-PocketTV/Other/Player-select.jpg?alt=media&token=42a59563-69ca-4048-81de-96d82fb952b0",
      "success_other_player_Permanent_message": "Congratulations!\nNow you can play video in outside player also."
    },
    "Paypal_Settings": {
      "currency": "USD",
      "paypal_client_id": "AayT8F3livDN4jjuSGdouX-JxGagYMgf5pAYK4df8Er1p4ysOhAdHvIYJhHH5cghzlVJrcne2OjyrTFA",
      "transaction_text": "Donate For RUTU"
    },
    "RateUs_Settings": {
      "delay_Activation_Milisecond": 5000,
      "initial_rateus_message": "Unlock It By giving good Ratings and Reviews US.",
      "sucess_rateus_message": "Congratulations!\nYou have sucessfully unlock."
    },
    "Remove_Ads_Setting": {
      "delay_Activation_Milisecond": 5000,
      "inapp_remove_ads_sku" : "com.pockettv.removeads",
      "initial_remove_ads_message": "If you want to remove ads permanently then \"PAYMENT\".\n\nIf you want to make this session ADS FREE, Then \"RATE US\" or \"SHARE APP\"",
      "is_Inapp_Purchase": false,
      "is_Rate": true,
      "is_Share": true,
      "success_remove_ads_Permanent_message": "Congratulations!\nNow Pocket TV is ADS FREE.",
      "success_remove_ads_message": "Congratulations!\nNow This session is ADS FREE."
    },
    "Settings": {
      "is_Searchbar": false,
      "is_Trial_Version": true,
      "trial_Version_Text": "",
      "trial_Version_Height": 70,
      "trial_Version_Bg_Color": "#000000",
      "trial_Version_Text_Color": "#ffffff",
      "developer_Id": "",
      "more_apps_url": "",
      "dummyURL": "https://www.efalia.com/wp-content/uploads/2015/01/fotolia_84282280-maquette-maintenance-2.jpg",
      "dummy_version": "1.0.0",
      "facebook_page_id": 822625707789265,
      "facebook_url": "https://www.facebook.com/",
      "isDummy": true,
      "is_texture_centercrop": false,
      "package_Id": "com.rutu.live.tv.nepal",
      "share_message": "Are you looking to Watch 2000+ Global Live TV Channels? Like Live Sports, News, Wild Life/Science, Religious, Kidz Channels in Full HD, Also you can see Popular TV Shows, Movies(Bollywood, Hollywood, Tollywood etc...), Video Songs Episodes (All Languages) then you should download : https://play.google.com/store/apps/details?id=com.rutu.live.tv.nepal",
      "texture_Bg_url": "https://raw.githubusercontent.com/rutumaster/Pocket-TV/Final-Apps/COMMON/Images-PocketTV/Intro%20Slider/texture/t5.png"
    },
    "Setup_Tv": {
      "app_already_dialog_message": "App already Install please find it and open it.",
      "app_already_dialog_title": "App Already Installed",
      "filename": "RUTU_TV.apk",
      "intro_btn_Color": "#c0392b",
      "is_Lock": true,
      "is_success_setup_btn_open_app": false,
      "is_texture_centercrop": false,
      "lock_btn_name": "Unlock Me",
      "lock_message": "Please unlock by pressing \"Unlock Me\" button.\n\nAfter that you able to setup.",
      "lock_title": "Unlock",
      "page_Color": "#2c3e50",
      "progress_download_message": "Downloading...",
      "progress_install_message": "Install Now",
      "setup_btn_Color": "#8eb021",
      "texture_Bg_url": "",
      "video_btn_Color": "#c0392b",
      "video_btn_title": "How to setup"
    },
    "Update_App": {
      "alert_message": "Please, update app to new version to continue reposting.",
      "alert_title": "New version available",
      "download_url": "",
      "filename": "RUTU.apk",
      "force": true,
      "is_system_browser": true,
      "progress_download_message": "Downloading...",
      "progress_install_message": "Install Now",
      "update_current_version": "1.0.0",
      "update_required": true,
      "update_store_app_id": "com.rutu.live.tv.nepal",
      "website_Url": "https://play.google.com/store/apps/details?id=com.rutu.live.tv.nepal"
    }
  }
}
